gpx2dzg/__init__.py
gpx2dzg/functions.py
gpx2dzg/gpx2dzg.py
gpx2dzg/help.py
gpx2dzg/io.py
gpx2dzg/plot.py
gpx2dzg/geoid/__init__.py
gpx2dzg/geoid/egm96-15.pgm
gpx2dzg-0.1.0.dist-info/LICENSE
gpx2dzg-0.1.0.dist-info/METADATA
gpx2dzg-0.1.0.dist-info/WHEEL
gpx2dzg-0.1.0.dist-info/entry_points.txt
gpx2dzg-0.1.0.dist-info/top_level.txt
gpx2dzg-0.1.0.dist-info/RECORD
