Metadata-Version: 2.1
Name: gpx2dzg
Version: 0.1.0
Summary: convert GPX files to GSSI's proprietary DZG format
Home-page: https://github.com/iannesbitt/gpx2dzg
Author: Ian Nesbitt
Author-email: ian.nesbitt@gmail.com
License: GPLv3
Platform: UNKNOWN
Classifier: Programming Language :: Python :: 3
Classifier: License :: OSI Approved :: GNU General Public License v3 (GPLv3)
Classifier: Operating System :: OS Independent
Classifier: Topic :: Scientific/Engineering :: Physics
Classifier: Intended Audience :: Science/Research
Classifier: Natural Language :: English
Classifier: Development Status :: 5 - Production/Stable
Requires-Dist: gpxpy
Requires-Dist: geomag
Requires-Dist: pynmea2
Requires-Dist: pygeodesy
Requires-Dist: readgssi
